executors/__init__.py
executors/blocking_executor.py
executors/executor.py
tlopo-executors/__init__.py
tlopo-executors/blocking_executor.py
tlopo-executors/executor.py
tlopo_executors/__init__.py
tlopo_executors/blocking_executor.py
tlopo_executors/executor.py
tlopo_executors-0.1.0.dist-info/METADATA
tlopo_executors-0.1.0.dist-info/WHEEL
tlopo_executors-0.1.0.dist-info/top_level.txt
tlopo_executors-0.1.0.dist-info/RECORD
