Metadata-Version: 2.1
Name: tlopo-executors
Version: 0.1.0
Summary: Simple package to show ip
Home-page: UNKNOWN
Author: UNKNOWN
Author-email: UNKNOWN
License: UNKNOWN
Platform: UNKNOWN
